[{"place": "NULL", "geo": "NULL", "valid": "False", "place_user": "NULL", "real": "True", "text": "RT @Maheeeeeennn___: 'Are you Okay'\nThey ask\n\nI respond \nas quickly \nas i can\nso they will not\nnotice the earthquakes\nin my voice \nor the t\u2026", "id": "1358034250440843269", "author_id": "1353971749080207363"}, {"place": "NULL", "geo": "NULL", "valid": "False", "place_user": "NULL", "real": "True", "text": "RT @angeliemrc: on d\u00e9clencherait des tsunamis si jamais on s\u2019unissait https://t.co/N2NFrDNSVM", "id": "1358034160212992002", "author_id": "1262858446900166665"}, {"place": "NULL", "geo": "NULL", "valid": "False", "place_user": "NULL", "real": "True", "text": "RT @Maheeeeeennn___: 'Are you Okay'\nThey ask\n\nI respond \nas quickly \nas i can\nso they will not\nnotice the earthquakes\nin my voice \nor the t\u2026", "id": "1358033757576511488", "author_id": "843794116974665729"}, {"place": "NULL", "geo": "NULL", "valid": "False", "place_user": "NULL", "real": "True", "text": "@JennaBellaJ I\u2019m good with no hurricanes, tsunamis, or a ton of scary venomous things that can kill me.", "id": "1358032919764340739", "author_id": "1216546498848198656"}, {"place": "NULL", "geo": "NULL", "valid": "False", "place_user": "NULL", "real": "True", "text": "RT @angeliemrc: on d\u00e9clencherait des tsunamis si jamais on s\u2019unissait https://t.co/N2NFrDNSVM", "id": "1358030910168383489", "author_id": "1339616073860214784"}, {"place": "NULL", "geo": "NULL", "valid": "False", "place_user": "NULL", "real": "True", "text": "@TheClaudiaBlack @yashar This is true for every emotional output .... even the positive ones. For example: ir is said that love blinds. That means your perception is narrowed or out of order. Without adequate perception curiosity will fail. curiosity may not coexist with emotional tsunamis + or -", "id": "1358029179003039744", "author_id": "1350501340670283776"}, {"place": "NULL", "geo": "NULL", "valid": "False", "place_user": "NULL", "real": "True", "text": "RT @angeliemrc: on d\u00e9clencherait des tsunamis si jamais on s\u2019unissait https://t.co/N2NFrDNSVM", "id": "1358028547579912194", "author_id": "1159005915405856768"}, {"place": "NULL", "geo": "NULL", "valid": "False", "place_user": "NULL", "real": "True", "text": "RT @arnaldozcajr: @o_antagonista Vendo como o sistema corrupto e as parcerias entre corruptos funcionam, at\u00e9 que a Lava Jato foi longe de m\u2026", "id": "1358027537549561858", "author_id": "715134804"}, {"place": "NULL", "geo": "NULL", "valid": "False", "place_user": "NULL", "real": "True", "text": "10 Most Powerful Tsunamis Of All Time #interesting https://t.co/7a7HIznwH4 #interesting #interest...\nhttps://t.co/7a7HIznwH4", "id": "1358020790399234049", "author_id": "468933098"}, {"place": "NULL", "geo": "NULL", "valid": "False", "place_user": "NULL", "real": "True", "text": "10 Most Powerful Tsunamis Of All Time #interesting https://t.co/XT06q13zEm #interesting #interest...\nhttps://t.co/XT06q13zEm", "id": "1358020789291933697", "author_id": "725357734107992064"}, {"place": "NULL", "geo": "NULL", "valid": "False", "place_user": "NULL", "real": "True", "text": "10 Most Powerful Tsunamis Of All Time #interesting https://t.co/uTFFAEIL3H #interesting #interest...\nhttps://t.co/uTFFAEIL3H", "id": "1358020788184637440", "author_id": "737287324879495172"}, {"place": "NULL", "geo": "NULL", "valid": "False", "place_user": "NULL", "real": "True", "text": "10 Most Powerful Tsunamis Of All Time #interesting https://t.co/I0COGQYhKL #interesting #interest...\nhttps://t.co/I0COGQYhKL", "id": "1358020787144429570", "author_id": "254314786"}, {"place": "NULL", "geo": "NULL", "valid": "False", "place_user": "NULL", "real": "True", "text": "10 Most Powerful Tsunamis Of All Time #interesting https://t.co/2YkLzwYtWg #interesting #interest...\nhttps://t.co/2YkLzwYtWg", "id": "1358020786104250370", "author_id": "1334501896900382721"}, {"place": "NULL", "geo": "NULL", "valid": "False", "place_user": "NULL", "real": "True", "text": "RT @KeeleGeology: Online Offer Holder Day @KeeleUniversity today. (Almost) live sessions with @hypocentre on tsunamis, @Agpaitic_Adam on vo\u2026", "id": "1358019836991873026", "author_id": "2918647549"}, {"place": "NULL", "geo": "NULL", "valid": "False", "place_user": "NULL", "real": "True", "text": "RT @KeeleGeology: Online Offer Holder Day @KeeleUniversity today. (Almost) live sessions with @hypocentre on tsunamis, @Agpaitic_Adam on vo\u2026", "id": "1358019586541633536", "author_id": "808428461362647040"}, {"place": "NULL", "geo": "NULL", "valid": "False", "place_user": "NULL", "real": "True", "text": "@deinTherapeut Ne, hab eher Tsunamis gemacht.", "id": "1358016892066287617", "author_id": "1316599806958227457"}, {"place": "NULL", "geo": "NULL", "valid": "False", "place_user": "NULL", "real": "True", "text": "@deinTherapeut Ne, ich habe immer Seismologe gespielt und Tsunamis verursacht -zum Leidwesen meiner Mutter", "id": "1358016634040897536", "author_id": "2709920367"}, {"place": "NULL", "geo": "NULL", "valid": "False", "place_user": "NULL", "real": "True", "text": "RT @angeliemrc: on d\u00e9clencherait des tsunamis si jamais on s\u2019unissait https://t.co/N2NFrDNSVM", "id": "1358015921944727558", "author_id": "1354905759121874948"}, {"place": "NULL", "geo": "NULL", "valid": "False", "place_user": "NULL", "real": "True", "text": "RT @INSIS_CNRS: #ResultatScientifique \ud83d\udd0e | Des tsunamis g\u00e9n\u00e9r\u00e9s \u00e0 l\u2019\u00e9chelle du laboratoire\n\n\u25b6\ufe0f https://t.co/e6i9Z0LS8f\n\ud83d\udcd5 @JFluidMech | https\u2026", "id": "1358014660675588096", "author_id": "109848011"}, {"place": "NULL", "geo": "NULL", "valid": "False", "place_user": "NULL", "real": "True", "text": "RT @angeliemrc: on d\u00e9clencherait des tsunamis si jamais on s\u2019unissait https://t.co/N2NFrDNSVM", "id": "1358014220793741312", "author_id": "1213155666631639040"}, {"place": "NULL", "geo": "NULL", "valid": "False", "place_user": "NULL", "real": "True", "text": "RT @angeliemrc: on d\u00e9clencherait des tsunamis si jamais on s\u2019unissait https://t.co/N2NFrDNSVM", "id": "1358013097231978496", "author_id": "1350074824174006279"}, {"place": "NULL", "geo": "NULL", "valid": "False", "place_user": "NULL", "real": "True", "text": "RT @angeliemrc: on d\u00e9clencherait des tsunamis si jamais on s\u2019unissait https://t.co/N2NFrDNSVM", "id": "1358012870894575620", "author_id": "1336391523269812226"}, {"place": "NULL", "geo": "NULL", "valid": "False", "place_user": "NULL", "real": "True", "text": "RT @angeliemrc: on d\u00e9clencherait des tsunamis si jamais on s\u2019unissait https://t.co/N2NFrDNSVM", "id": "1358012139689160704", "author_id": "1281370259367383040"}, {"place": "NULL", "geo": "NULL", "valid": "False", "place_user": "NULL", "real": "True", "text": "RT @INSIS_CNRS: #ResultatScientifique \ud83d\udd0e | Des tsunamis g\u00e9n\u00e9r\u00e9s \u00e0 l\u2019\u00e9chelle du laboratoire\n\n\u25b6\ufe0f https://t.co/e6i9Z0LS8f\n\ud83d\udcd5 @JFluidMech | https\u2026", "id": "1358011219869851648", "author_id": "995791838"}, {"place": "NULL", "geo": "NULL", "valid": "False", "place_user": "NULL", "real": "True", "text": "RT @INSIS_CNRS: #ResultatScientifique \ud83d\udd0e | Des tsunamis g\u00e9n\u00e9r\u00e9s \u00e0 l\u2019\u00e9chelle du laboratoire\n\n\u25b6\ufe0f https://t.co/e6i9Z0LS8f\n\ud83d\udcd5 @JFluidMech | https\u2026", "id": "1358010613499387906", "author_id": "842814927379333120"}, {"place": "NULL", "geo": "NULL", "valid": "False", "place_user": "NULL", "real": "True", "text": "RT @angeliemrc: on d\u00e9clencherait des tsunamis si jamais on s\u2019unissait https://t.co/N2NFrDNSVM", "id": "1358009161125093376", "author_id": "1063780685616476161"}, {"place": "NULL", "geo": "NULL", "valid": "False", "place_user": "NULL", "real": "True", "text": "RT @angeliemrc: on d\u00e9clencherait des tsunamis si jamais on s\u2019unissait https://t.co/N2NFrDNSVM", "id": "1358008410936082432", "author_id": "1297567807819976705"}, {"place": "NULL", "geo": "NULL", "valid": "False", "place_user": "NULL", "real": "True", "text": "RT @INSIS_CNRS: #ResultatScientifique \ud83d\udd0e | Des tsunamis g\u00e9n\u00e9r\u00e9s \u00e0 l\u2019\u00e9chelle du laboratoire\n\n\u25b6\ufe0f https://t.co/e6i9Z0LS8f\n\ud83d\udcd5 @JFluidMech | https\u2026", "id": "1358008035294199809", "author_id": "143909021"}, {"place": "NULL", "geo": "NULL", "valid": "False", "place_user": "NULL", "real": "True", "text": "RT @cackerman1: Earthquakes, Tsunamis and Nuclear Risks\n\nPrediction and Assessment Beyond the Fukushima Accident\n\nhttps://t.co/aP0wb59kUy h\u2026", "id": "1358005416907714561", "author_id": "103040317"}, {"place": {"West": 0.3922}, "geo": "NULL", "valid": "False", "place_user": "NULL", "real": "True", "text": "@felixiaoi That might actually be a cool legend \ud83d\ude02\nTsunamis are caused by the West and East Demon Lords fighting.", "id": "1358005158521655304", "author_id": "759366377618550784"}, {"place": "NULL", "geo": "NULL", "valid": "False", "place_user": "NULL", "real": "True", "text": "@garethicke i once made a joke that Covid would soon be blamed for earthquakes, tsunamis and volcano eruptions. Hasn't happened in the lamestream media yet, but i am sticking to my word", "id": "1358004849149845506", "author_id": "124837023"}, {"place": "NULL", "geo": "NULL", "valid": "False", "place_user": "NULL", "real": "True", "text": "RT @angeliemrc: on d\u00e9clencherait des tsunamis si jamais on s\u2019unissait https://t.co/N2NFrDNSVM", "id": "1358004211108241409", "author_id": "1214681167858950156"}, {"place": "NULL", "geo": "NULL", "valid": "False", "place_user": "NULL", "real": "True", "text": "Earthquakes, Tsunamis and Nuclear Risks\n\nPrediction and Assessment Beyond the Fukushima Accident\n\nhttps://t.co/aP0wb59kUy https://t.co/lpMImiZoAY", "id": "1358004081793650688", "author_id": "365436644"}, {"place": "NULL", "geo": "NULL", "valid": "False", "place_user": "NULL", "real": "True", "text": "RT @angeliemrc: on d\u00e9clencherait des tsunamis si jamais on s\u2019unissait https://t.co/N2NFrDNSVM", "id": "1358004016429596673", "author_id": "1025141057787441152"}, {"place": "NULL", "place_user": "S\u00e3o Paulo, Br\u00e9sil", "geo": "NULL", "valid": "True", "real": "True", "text": "@diogomainardi Vendo como o sistema corrupto e as parcerias entre corruptos funcionam, at\u00e9 que a Lava Jato foi longe de mais! Era pedir muito que al\u00e9m disso fosse tamb\u00e9m duradoura! A Lava Jato foi um tsunami para os corruptos. Precisa existir outros tsunamis desse de tempos em tempos!", "id": "1358003877992357890", "author_id": "99572003"}, {"place": "NULL", "geo": "NULL", "valid": "False", "place_user": "NULL", "real": "True", "text": "RT @angeliemrc: on d\u00e9clencherait des tsunamis si jamais on s\u2019unissait https://t.co/N2NFrDNSVM", "id": "1358003745234313219", "author_id": "757989485468614656"}, {"place": "NULL", "place_user": "S\u00e3o Paulo, Br\u00e9sil", "geo": "NULL", "valid": "True", "real": "True", "text": "@o_antagonista Vendo como o sistema corrupto e as parcerias entre corruptos funcionam, at\u00e9 que a Lava Jato foi longe de mais! Era pedir muito que al\u00e9m disso fosse tamb\u00e9m duradoura! A Lava Jato foi um tsunami para os corruptos. Precisa existir outros tsunamis desse de tempos em tempos!", "id": "1358003677563416577", "author_id": "99572003"}, {"place": "NULL", "geo": "NULL", "valid": "False", "place_user": "NULL", "real": "True", "text": "RT @angeliemrc: on d\u00e9clencherait des tsunamis si jamais on s\u2019unissait https://t.co/N2NFrDNSVM", "id": "1358002914426564610", "author_id": "1085642609714966528"}, {"place": "NULL", "geo": "NULL", "valid": "False", "place_user": "NULL", "real": "True", "text": "RT @angeliemrc: on d\u00e9clencherait des tsunamis si jamais on s\u2019unissait https://t.co/N2NFrDNSVM", "id": "1358002569323372547", "author_id": "1015427396105891841"}, {"place": "NULL", "geo": "NULL", "valid": "False", "place_user": "NULL", "real": "True", "text": "@euronewses Me gusta mucho la idea y el prop\u00f3sito de este edificio, pero no me gusta su arquitectura, es una arquitectura basada en la imagen y no en la lucha contra temporales peligrosos, construyan pensando en los tsunamis y como superarlos, d\u00e9jense de cosas bonitas.", "id": "1358001519971434503", "author_id": "1357992671164461058"}, {"place": {"Sant Mart\u00ed Tucans": 0.5444}, "geo": "NULL", "valid": "False", "place_user": "NULL", "real": "True", "text": "Sant Mart\u00ed Tucans - Tsunamis https://t.co/TGyViQRZcD v\u00eda @YouTube", "id": "1358000515204972546", "author_id": "1260252306886529028"}, {"place": "NULL", "geo": "NULL", "valid": "False", "place_user": "NULL", "real": "True", "text": "Online Offer Holder Day @KeeleUniversity today. (Almost) live sessions with @hypocentre on tsunamis, @Agpaitic_Adam on volcanoes, hosted by @stuart_egan at 1pm. https://t.co/kZUxxmj4sI", "id": "1357999248277667840", "author_id": "74688544"}, {"place": "NULL", "geo": "NULL", "valid": "False", "place_user": "NULL", "real": "True", "text": "@E_Mbuyazi @iam_ThePaulo Like Tsunamis, earthquakes, volcanic eruptions etc. Is that the purpose of God's love towards mankind?", "id": "1357995037368455168", "author_id": "807183732"}, {"place": "NULL", "geo": "NULL", "valid": "False", "place_user": "NULL", "real": "True", "text": "RT @angeliemrc: on d\u00e9clencherait des tsunamis si jamais on s\u2019unissait https://t.co/N2NFrDNSVM", "id": "1357994396113924097", "author_id": "1141032105545293825"}, {"place": "NULL", "geo": "NULL", "valid": "False", "place_user": "NULL", "real": "True", "text": "RT @angeliemrc: on d\u00e9clencherait des tsunamis si jamais on s\u2019unissait https://t.co/N2NFrDNSVM", "id": "1357993731920715778", "author_id": "1266399584286380035"}, {"place": "NULL", "geo": "NULL", "valid": "False", "place_user": "NULL", "real": "True", "text": "RT @angeliemrc: on d\u00e9clencherait des tsunamis si jamais on s\u2019unissait https://t.co/N2NFrDNSVM", "id": "1357993277291651073", "author_id": "1175798149052620800"}, {"place": "NULL", "geo": "NULL", "valid": "False", "place_user": "NULL", "real": "True", "text": "RT @angeliemrc: on d\u00e9clencherait des tsunamis si jamais on s\u2019unissait https://t.co/N2NFrDNSVM", "id": "1357992904912961537", "author_id": "1317389506392313856"}, {"place": "NULL", "geo": "NULL", "valid": "False", "place_user": "NULL", "real": "True", "text": "Indigenous rights of the Onge tribe, the most important nesting site for the Giant Leatherback sea turtle, \nand vulnerability to earthquakes and tsunamis. #SaveLittleAndaman\nThanks @shivya \n\n@patagonia \n@restorm https://t.co/nIK8WwXG7F", "id": "1357992502008057856", "author_id": "2317591962"}, {"place": "NULL", "geo": "NULL", "valid": "False", "place_user": "NULL", "real": "True", "text": "RT @angeliemrc: on d\u00e9clencherait des tsunamis si jamais on s\u2019unissait https://t.co/N2NFrDNSVM", "id": "1357991571166216192", "author_id": "1070375594284773376"}]